Workbook
Name Aporte: simulador!$C$15
Name Patrimonio: simulador!$C$18
Name QtsAnos: simulador!$C$16
Name RendCarteira: simulador!$D$11
Name Salario: simulador!$D$10
Name SugestaoInvestimento: simulador!$D$12
Name TaxaMensal: simulador!$C$17

Sheet simulador
B9: Este simulador estima o crescimento dos investimentos com base em aportes mensais e taxa de rendimento, permitindo visualizar o patrimônio acumulado e a renda mensal estimada ao longo do tempo. | C9: CONFIGURAÇÕES
C10: Salário | D10: 12000
C11: Rendimento Carteira | D11: 0.006
C12: Sugestão de Investimento | D12: =D10* 30% -> 3600
B14: SIMULADOR MENSAL
B15: Quanto investir por mês | C15: 3600
B16: Por quantos anos | C16: 5
B17: Taxa de rendimento mensal | C17: 0.011
B18: Patrimônio Acumulado | C18: =FV(TaxaMensal,QtsAnos*12,Aporte)*-1 -> 303654.33
B20: Dividendos Mensais | C20: =Patrimonio*RendCarteira -> 1821.926
B23: Projeções considerando os mesmos parâmetros de investimento | D23: Dividendos
A24: 2 | B24: Acumulado em 2 anos | C24: =FV($C17,$A24*12,$C15) *-1 -> 98264.491 | D24: =C24*D11 -> 589.58694
A25: 5 | B25: Acumulado em 5 anos | C25: =FV($C17,$A25*12,$C15) *-1 -> 303654.33 | D25: =C25*D11 -> 1821.926
A26: 10 | B26: Acumulado em 10 anos | C26: =FV($C17,$A26*12,$C15) *-1 -> 889049.06 | D26: =C26*D11 -> 5334.2944
A27: 20 | B27: Acumulado em 20 anos | C27: =FV($C17,$A27*12,$C15) *-1 -> 4193234.4 | D27: =C27*D11 -> 25159.406
A28: 30 | B28: Acumulado em 30 anos | C28: =FV($C17,$A28*12,$C15) *-1 -> 16473367 | D28: =C28*D11 -> 98840.204
B30: PERFIL | C30: MODERADO
B31: VALOR A SER INVESTIDO POR MÊS | C31: =Aporte -> 3600
B32: TIPO DE FII | C32: Percentual Sugerido | D32: Valores
B33: PAPEL | C33: =VLOOKUP($C$30&"-"&B33,Tab_aux!$A$1:$D$20,4,FALSE) -> 0.32 | D33: =C33*Aporte -> 1152
B34: TIJOLO | C34: =VLOOKUP($C$30&"-"&B34,Tab_aux!$A$1:$D$20,4,FALSE) -> 0.35 | D34: =C34*Aporte -> 1260
B35: HÍBRIDOS | C35: =VLOOKUP($C$30&"-"&B35,Tab_aux!$A$1:$D$20,4,FALSE) -> 0.08 | D35: =C35*Aporte -> 288
B36: FOFs | C36: =VLOOKUP($C$30&"-"&B36,Tab_aux!$A$1:$D$20,4,FALSE) -> 0.05 | D36: =C36*Aporte -> 180
B37: DESENVOLVIMENTO | C37: =VLOOKUP($C$30&"-"&B37,Tab_aux!$A$1:$D$20,4,FALSE) -> 0.1 | D37: =C37*Aporte -> 360
B38: HOTELARIAS | C38: =VLOOKUP($C$30&"-"&B38,Tab_aux!$A$1:$D$20,4,FALSE) -> 0.1 | D38: =C38*Aporte -> 360
D39: =SUM(D33:D38) -> 3600

Sheet Tab_aux
A2: CHAVE | B2: PERFIL | C2: TIPO DE FII | D2: %
A3: Conservador-PAPEL | B3: Conservador | C3: PAPEL | D3: 0.3 | H3: %
A4: Conservador-TIJOLO | B4: Conservador | C4: TIJOLO | D4: 0.5 | G4: Moderado-TIJOLO | H4: =VLOOKUP(G4,$A$1:$D$20,4,FALSE) -> 0.35
A5: Conservador-HÍBRIDOS | B5: Conservador | C5: HÍBRIDOS | D5: 0.1
A6: Conservador-FOFs | B6: Conservador | C6: FOFs | D6: 0.1
A7: Conservador-DESENVOLVIMENTO | B7: Conservador | C7: DESENVOLVIMENTO | D7: 0
A8: Conservador-HOTELARIAS | B8: Conservador | C8: HOTELARIAS | D8: 0
A9: Moderado-PAPEL | B9: Moderado | C9: PAPEL | D9: 0.32
A10: Moderado-TIJOLO | B10: Moderado | C10: TIJOLO | D10: 0.35
A11: Moderado-HÍBRIDOS | B11: Moderado | C11: HÍBRIDOS | D11: 0.08
A12: Moderado-FOFs | B12: Moderado | C12: FOFs | D12: 0.05
A13: Moderado-DESENVOLVIMENTO | B13: Moderado | C13: DESENVOLVIMENTO | D13: 0.1
A14: Moderado-HOTELARIAS | B14: Moderado | C14: HOTELARIAS | D14: 0.1
A15: Agressivo-PAPEL | B15: Agressivo | C15: PAPEL | D15: 0.5
A16: Agressivo-TIJOLO | B16: Agressivo | C16: TIJOLO | D16: 0.1
... A20: Agressivo-HOTELARIAS | B20: Agressivo | C20: HOTELARIAS | D20: 0.1
